pyworks_cache/__init__.py
pyworks_cache/main.py
pyworks_cache-0.1.0a1.dist-info/LICENSE
pyworks_cache-0.1.0a1.dist-info/WHEEL
pyworks_cache-0.1.0a1.dist-info/METADATA
pyworks_cache-0.1.0a1.dist-info/RECORD
